{
  "products": [
    {
      "id": 1,
      "productCode": "TERM_20",
      "name": "20 Year Term Life",
      "minAge": 18,
      "maxAge": 60,
      "coverages": [100000, 250000, 500000],
      "terms": [10, 20, 30]
    },
    {
      "id": 2,
      "productCode": "TERM_30",
      "name": "30 Year Term Life",
      "minAge": 25,
      "maxAge": 55,
      "coverages": [250000, 500000, 1000000],
      "terms": [20, 30]
    }
  ],
  "quotes": [
    {
      "id": 1,
      "age": 35,
      "smoker": false,
      "term": 20,
      "coverage": 250000,
      "monthlyPremium": 42.75,
      "carrier": "ABC Life"
    }
  ]
}
